whoisfreaks/__init__.py
whoisfreaks/client.py
whoisfreaks/core/__init__.py
whoisfreaks/core/api_error.py
whoisfreaks/core/client_wrapper.py
whoisfreaks/core/datetime_utils.py
whoisfreaks/core/file.py
whoisfreaks/core/http_client.py
whoisfreaks/core/http_response.py
whoisfreaks/core/jsonable_encoder.py
whoisfreaks/core/pydantic_utilities.py
whoisfreaks/core/query_encoder.py
whoisfreaks/core/remove_none_from_dict.py
whoisfreaks/core/request_options.py
whoisfreaks/core/serialization.py
whoisfreaks/environment.py
whoisfreaks/errors/__init__.py
whoisfreaks/errors/bad_request_error.py
whoisfreaks/errors/content_too_large_error.py
whoisfreaks/errors/forbidden_error.py
whoisfreaks/errors/gateway_timeout_error.py
whoisfreaks/errors/internal_server_error.py
whoisfreaks/errors/not_found_error.py
whoisfreaks/errors/precondition_failed_error.py
whoisfreaks/errors/request_timeout_error.py
whoisfreaks/errors/service_unavailable_error.py
whoisfreaks/errors/too_many_requests_error.py
whoisfreaks/errors/unauthorized_error.py
whoisfreaks/py.typed
whoisfreaks/raw_client.py
whoisfreaks/types/__init__.py
whoisfreaks/types/bad_request_error_body.py
whoisfreaks/types/content_too_large_error_body.py
whoisfreaks/types/forbidden_error_body.py
whoisfreaks/types/gateway_timeout_error_body.py
whoisfreaks/types/get_v_10_asn_whois_response.py
whoisfreaks/types/get_v_10_asn_whois_response_administrative_contacts_item.py
whoisfreaks/types/get_v_10_asn_whois_response_as_blocks_item.py
whoisfreaks/types/get_v_10_asn_whois_response_aut_nums_item.py
whoisfreaks/types/get_v_10_asn_whois_response_organization.py
whoisfreaks/types/get_v_10_asn_whois_response_technical_contacts_item.py
whoisfreaks/types/get_v_10_domain_availability_response.py
whoisfreaks/types/get_v_10_domain_availability_response_domain_available_response_item.py
whoisfreaks/types/get_v_10_ip_whois_response.py
whoisfreaks/types/get_v_10_ip_whois_response_abuse_contacts_item.py
whois_sdk_openapi-0.0.43.dist-info/METADATA
whois_sdk_openapi-0.0.43.dist-info/WHEEL
whois_sdk_openapi-0.0.43.dist-info/RECORD
